Metadata-Version: 1.0
Name: vvs-distributions
Version: 0.1
Summary: Gaussian and Binomial distributions
Home-page: UNKNOWN
Author: Vamsee Sundar
Author-email: vvippart@asu.edu
License: UNKNOWN
Platform: UNKNOWN
